<response>
  <sectors cand_name="Seth Moulton (D)" cid="N00035431" cycle="2014" origin="Center for Responsive Politics" source="http://www.opensecrets.org/member-of-congress/industries?cid=N00035431&amp;cycle=2014" last_updated="02/27/2017">
    <sector sector_name="Agribusiness" sectorid="A" indivs="14500" pacs="1000" total="15500"/>
    <sector sector_name="Communic/Electronics" sectorid="B" indivs="44250" pacs="5000" total="49250"/>
    <sector sector_name="Construction" sectorid="C" indivs="12550" pacs="0" total="12550"/>
    <sector sector_name="Defense" sectorid="D" indivs="6200" pacs="7000" total="13200"/>
    <sector sector_name="Energy/Nat Resource" sectorid="E" indivs="11050" pacs="0" total="11050"/>
    <sector sector_name="Finance/Insur/RealEst" sectorid="F" indivs="415217" pacs="24500" total="439717"/>
    <sector sector_name="Health" sectorid="H" indivs="54685" pacs="15750" total="70435"/>
    <sector sector_name="Lawyers &amp; Lobbyists" sectorid="K" indivs="110900" pacs="18500" total="129400"/>
    <sector sector_name="Transportation" sectorid="M" indivs="17350" pacs="3500" total="20850"/>
    <sector sector_name="Misc Business" sectorid="N" indivs="96607" pacs="9830" total="106437"/>
    <sector sector_name="Labor" sectorid="P" indivs="1000" pacs="107500" total="108500"/>
    <sector sector_name="Ideology/Single-Issue" sectorid="Q" indivs="1196469" pacs="178140" total="1374609"/>
    <sector sector_name="Other" sectorid="W" indivs="224780" pacs="500" total="225280"/>
  </sectors>
</response>
