<response>
  <sectors cand_name="Johnny Isakson (R)" cid="N00002593" cycle="2016" origin="Center for Responsive Politics" source="http://www.opensecrets.org/member-of-congress/industries?cid=N00002593&amp;cycle=2016" last_updated="11/27/2017">
    <sector sector_name="Agribusiness" sectorid="A" indivs="224699" pacs="294800" total="519499"/>
    <sector sector_name="Communic/Electronics" sectorid="B" indivs="99650" pacs="199200" total="298850"/>
    <sector sector_name="Construction" sectorid="C" indivs="186918" pacs="140200" total="327118"/>
    <sector sector_name="Defense" sectorid="D" indivs="13850" pacs="68000" total="81850"/>
    <sector sector_name="Energy/Nat Resource" sectorid="E" indivs="167050" pacs="188500" total="355550"/>
    <sector sector_name="Finance/Insur/RealEst" sectorid="F" indivs="1462216" pacs="714250" total="2176466"/>
    <sector sector_name="Health" sectorid="H" indivs="279075" pacs="624350" total="903425"/>
    <sector sector_name="Lawyers &amp; Lobbyists" sectorid="K" indivs="605703" pacs="132020" total="737723"/>
    <sector sector_name="Transportation" sectorid="M" indivs="277724" pacs="181000" total="458724"/>
    <sector sector_name="Misc Business" sectorid="N" indivs="646232" pacs="492116" total="1138348"/>
    <sector sector_name="Labor" sectorid="P" indivs="0" pacs="27000" total="27000"/>
    <sector sector_name="Ideology/Single-Issue" sectorid="Q" indivs="253695" pacs="476500" total="730195"/>
    <sector sector_name="Other" sectorid="W" indivs="688499" pacs="13000" total="701499"/>
  </sectors>
</response>
