<response>
  <industries cand_name="French Hill (R)" cid="N00035792" cycle="2016" origin="Center for Responsive Politics" source="https://www.opensecrets.org/members-of-congress/industries?cid=N00035792&amp;cycle=2016" last_updated="11/27/2017">
    <industry industry_code="F07" industry_name="Securities &amp; Investment" indivs="130175" pacs="126350" total="256525"/>
    <industry industry_code="F03" industry_name="Commercial Banks" indivs="80475" pacs="114750" total="195225"/>
    <industry industry_code="W06" industry_name="Retired" indivs="147825" pacs="0" total="147825"/>
    <industry industry_code="F09" industry_name="Insurance" indivs="19500" pacs="123000" total="142500"/>
    <industry industry_code="F10" industry_name="Real Estate" indivs="33850" pacs="86000" total="119850"/>
    <industry industry_code="H01" industry_name="Health Professionals" indivs="75650" pacs="23000" total="98650"/>
    <industry industry_code="Q10" industry_name="Misc Issues" indivs="79750" pacs="100" total="79850"/>
    <industry industry_code="K01" industry_name="Lawyers/Law Firms" indivs="51082" pacs="11000" total="62082"/>
    <industry industry_code="Q03" industry_name="Leadership PACs" indivs="0" pacs="58282" total="58282"/>
    <industry industry_code="F11" industry_name="Accountants" indivs="16150" pacs="41500" total="57650"/>
  </industries>
</response>
